serpapi_async/__init__.py
serpapi_async/apple_app_store_search.py
serpapi_async/baidu_search.py
serpapi_async/bing_search.py
serpapi_async/constant.py
serpapi_async/duck_duck_go_search.py
serpapi_async/ebay_search.py
serpapi_async/google_scholar_search.py
serpapi_async/google_search.py
serpapi_async/google_search_aiohttp.py
serpapi_async/home_depot_search.py
serpapi_async/naver_search.py
serpapi_async/pagination.py
serpapi_async/serp_api_client.py
serpapi_async/serp_api_client_aiohttp.py
serpapi_async/serp_api_client_exception.py
serpapi_async/walmart_search.py
serpapi_async/yahoo_search.py
serpapi_async/yandex_search.py
serpapi_async/youtube_search.py
google_search_results_async-2.4.2.dist-info/LICENSE
google_search_results_async-2.4.2.dist-info/METADATA
google_search_results_async-2.4.2.dist-info/WHEEL
google_search_results_async-2.4.2.dist-info/top_level.txt
google_search_results_async-2.4.2.dist-info/RECORD
