Metadata-Version: 2.1
Name: google-search-results-async
Version: 2.4.2
Summary: Scrape and search localized results from Google, Bing, Baidu, Yahoo, Yandex, Ebay, Homedepot, youtube at scale using SerpApi.com
Home-page: https://github.com/serpapi/google-search-results-python
Author: Matteo Senardi
Author-email: pualien@gmail.com
License: MIT
Keywords: scrape,serp,api,json,search,localized,rank,google,bing,baidu,yandex,yahoo,ebay,scale,datamining,training,machine,ml,youtube,naver,walmart,apple,store,app
Platform: UNKNOWN
Classifier: License :: OSI Approved :: MIT License
Classifier: Programming Language :: Python :: 3.5
Classifier: Programming Language :: Python :: 3.6
Classifier: Programming Language :: Python :: 3.7
Classifier: Programming Language :: Python :: 3.8
Classifier: Programming Language :: Python :: 3.9
Classifier: Natural Language :: English
Classifier: Topic :: Utilities
Requires-Python: >=3.5
License-File: LICENSE
Requires-Dist: requests (==2.25.1)
Requires-Dist: Brotli (==1.0.9)
Requires-Dist: aiodns (==3.0.0)
Requires-Dist: aiohttp (==3.8.1)
Requires-Dist: cchardet (==2.1.7)
